EasyDictDB/__init__.py
EasyDictDB/main.py
EasyDictDB-1.1.0.dist-info/METADATA
EasyDictDB-1.1.0.dist-info/WHEEL
EasyDictDB-1.1.0.dist-info/top_level.txt
EasyDictDB-1.1.0.dist-info/RECORD
