Metadata-Version: 2.1
Name: EasyDictDB
Version: 1.1.0
Summary: A simple library to save and load Python dictionaries in SQLite.
Home-page: https://github.com/mmd-dll/EasyDictDB
Author: mohammad reza
Author-email: id.suzuya@gmail.com
Classifier: Programming Language :: Python :: 3
Classifier: License :: OSI Approved :: MIT License
Classifier: Operating System :: OS Independent
Requires-Python: >=3.6
